noprint/__init__.py
noprint/cli.py
noprint/exceptions.py
noprint/logger.py
noprint/module.py
noprint/sprint.py
noprint-3.1.1.dist-info/LICENSE
noprint-3.1.1.dist-info/METADATA
noprint-3.1.1.dist-info/WHEEL
noprint-3.1.1.dist-info/entry_points.txt
noprint-3.1.1.dist-info/top_level.txt
noprint-3.1.1.dist-info/RECORD
