Metadata-Version: 2.1
Name: noprint
Version: 3.1.1
Summary: Do not allow prints in your code
Author-email: Radoslaw Gryta <radek.gryta@gmail.com>
Project-URL: Homepage, https://github.com/rgryta/NoPrint
Project-URL: Bug Tracker, https://github.com/rgryta/NoPrint/issues
Classifier: Programming Language :: Python :: 3
Classifier: License :: OSI Approved :: MIT License
Classifier: Operating System :: OS Independent
Requires-Python: >=3.7
License-File: LICENSE
